flask_diced
